pautobot/__init__.py
pautobot/app.py
pautobot/app_info.py
pautobot/config.py
pautobot/database.py
pautobot/db_models.py
pautobot/globals.py
pautobot/models.py
pautobot/utils.py
pautobot/engine/__init__.py
pautobot/engine/bot_context.py
pautobot/engine/bot_enums.py
pautobot/engine/chatbot_factory.py
pautobot/engine/context_manager.py
pautobot/engine/engine.py
pautobot/engine/ingest.py
pautobot/engine/llm_factory.py
pautobot/engine/qa_factory.py
pautobot/frontend-dist/404.html
pautobot/frontend-dist/favicon.ico
pautobot/frontend-dist/index.html
pautobot/frontend-dist/loading.svg
pautobot/frontend-dist/pautobot.png
pautobot/frontend-dist/_next/static/Xk-4lwAybgzClHcBAEzo7/_buildManifest.js
pautobot/frontend-dist/_next/static/Xk-4lwAybgzClHcBAEzo7/_ssgManifest.js
pautobot/frontend-dist/_next/static/chunks/framework-2c16ac744b6cdea6.js
pautobot/frontend-dist/_next/static/chunks/main-be89c515900796e7.js
pautobot/frontend-dist/_next/static/chunks/polyfills-78c92fac7aa8fdd8.js
pautobot/frontend-dist/_next/static/chunks/webpack-8fa1640cc84ba8fe.js
pautobot/frontend-dist/_next/static/chunks/pages/_app-c60cf4cd54f10591.js
pautobot/frontend-dist/_next/static/chunks/pages/_error-77823ddac6993d35.js
pautobot/frontend-dist/_next/static/chunks/pages/index-7d6f54679609ba64.js
pautobot/frontend-dist/_next/static/css/17d8f17aea26a79b.css
pautobot/frontend-dist/_next/static/media/037c6ceced78c87a-s.woff2
pautobot/frontend-dist/_next/static/media/03a2ebda46411260-s.woff2
pautobot/frontend-dist/_next/static/media/2cffe11a47028c14-s.woff2
pautobot/frontend-dist/_next/static/media/4ab03c045edad786-s.p.woff2
pautobot/frontend-dist/_next/static/media/4cf1eda6528c4545-s.p.woff2
pautobot/frontend-dist/_next/static/media/51fbb2aa5ef2b5cf-s.woff2
pautobot/frontend-dist/_next/static/media/560bcc4e09749527-s.woff2
pautobot/frontend-dist/_next/static/media/6cb9e821df97febd-s.p.woff2
pautobot/frontend-dist/_next/static/media/723f3c07bb1fbaab-s.woff2
fastagi-0.0.27.dist-info/METADATA
fastagi-0.0.27.dist-info/WHEEL
fastagi-0.0.27.dist-info/entry_points.txt
fastagi-0.0.27.dist-info/top_level.txt
fastagi-0.0.27.dist-info/RECORD
