Metadata-Version: 2.1
Name: fastagi
Version: 0.0.27
Summary: Private AutoGPT Robot - Your private task assistant with GPT!
Home-page: https://github.com/vietanhdev/pautobot
Author: Viet-Anh Nguyen
Author-email: vietanh.dev@gmail.com
License: Apache License 2.0
Keywords: Personal Assistant,Automation,GPT,LLM,PrivateGPT
Classifier: Natural Language :: English
Classifier: Operating System :: OS Independent
Classifier: Programming Language :: Python
Classifier: Programming Language :: Python :: 3.8
Classifier: Programming Language :: Python :: 3.9
Classifier: Programming Language :: Python :: 3.10
Classifier: Programming Language :: Python :: 3.11
Classifier: Programming Language :: Python :: 3 :: Only
Requires-Dist: langchain >=0.0.194
Requires-Dist: gpt4all >=0.3.0
Requires-Dist: chromadb >=0.3.23
Requires-Dist: urllib3 >=2.0.2
Requires-Dist: pdfminer.six >=20221105
Requires-Dist: unstructured >=0.6.6
Requires-Dist: extract-msg >=0.41.1
Requires-Dist: tabulate >=0.9.0
Requires-Dist: pandoc >=2.3
Requires-Dist: pypandoc >=1.11
Requires-Dist: tqdm >=4.65.0
Requires-Dist: python-multipart >=0.0.6
Requires-Dist: fastapi ==0.96.0
Requires-Dist: SQLAlchemy ==2.0.15
Requires-Dist: alembic ==1.11.1
Requires-Dist: sentence-transformers ==2.2.2
Requires-Dist: requests
